odoo/addons/purchase_order_line_stock_available/README.rst
odoo/addons/purchase_order_line_stock_available/__init__.py
odoo/addons/purchase_order_line_stock_available/__manifest__.py
odoo/addons/purchase_order_line_stock_available/i18n/es.po
odoo/addons/purchase_order_line_stock_available/i18n/fr.po
odoo/addons/purchase_order_line_stock_available/i18n/fr_FR.po
odoo/addons/purchase_order_line_stock_available/i18n/pt_BR.po
odoo/addons/purchase_order_line_stock_available/i18n/purchase_order_line_stock_available.pot
odoo/addons/purchase_order_line_stock_available/i18n/sl.po
odoo/addons/purchase_order_line_stock_available/models/__init__.py
odoo/addons/purchase_order_line_stock_available/models/purchase.py
odoo/addons/purchase_order_line_stock_available/readme/CONTRIBUTORS.rst
odoo/addons/purchase_order_line_stock_available/readme/DESCRIPTION.rst
odoo/addons/purchase_order_line_stock_available/readme/USAGE.rst
odoo/addons/purchase_order_line_stock_available/static/description/icon.png
odoo/addons/purchase_order_line_stock_available/static/description/index.html
odoo/addons/purchase_order_line_stock_available/views/purchase_view.xml
odoo12_addon_purchase_order_line_stock_available-12.0.1.0.0.99.dev12.dist-info/METADATA
odoo12_addon_purchase_order_line_stock_available-12.0.1.0.0.99.dev12.dist-info/WHEEL
odoo12_addon_purchase_order_line_stock_available-12.0.1.0.0.99.dev12.dist-info/top_level.txt
odoo12_addon_purchase_order_line_stock_available-12.0.1.0.0.99.dev12.dist-info/RECORD
